rest_captcha/.DS_Store
rest_captcha/__init__.py
rest_captcha/captcha.py
rest_captcha/captcha_py2.png
rest_captcha/captcha_py3.png
rest_captcha/fonts/COPYRIGHT.TXT
rest_captcha/fonts/README.TXT
rest_captcha/fonts/Vera.ttf
rest_captcha/serializers.py
rest_captcha/settings.py
rest_captcha/tests.py
rest_captcha/urls.py
rest_captcha/utils.py
rest_captcha/views.py
drf_captcha-0.2.1.dist-info/LICENSE
drf_captcha-0.2.1.dist-info/METADATA
drf_captcha-0.2.1.dist-info/WHEEL
drf_captcha-0.2.1.dist-info/RECORD
