Metadata-Version: 2.1
Name: drf-captcha
Version: 0.2.1
Summary: A - hopefully maintained - fork of django-simple-captcha to keep up with upgrading dependencies
License: MIT
Author: evgeny.zuev
Author-email: zueves@gmail.com
Maintainer: omeraksoy
Maintainer-email: omer.aksoy@lifemote.com
Requires-Python: >=3.8,<4.0
Classifier: License :: OSI Approved :: MIT License
Classifier: Programming Language :: Python :: 3
Classifier: Programming Language :: Python :: 3.8
Classifier: Programming Language :: Python :: 3.9
Classifier: Programming Language :: Python :: 3.10
Classifier: Programming Language :: Python :: 3.11
Classifier: Programming Language :: Python :: 3.12
Requires-Dist: Pillow
Requires-Dist: django (<6.0)
Requires-Dist: djangorestframework (>=3,<4)
